.travis.yml
LICENSE.md
MANIFEST.in
Makefile
README.md
pylama.ini
pytest.ini
requirements.dev.txt
requirements.txt
setup.cfg
setup.py
tox.ini
datapackage_pipelines_aws/VERSION
datapackage_pipelines_aws/__init__.py
datapackage_pipelines_aws/helpers.py
datapackage_pipelines_aws/s3_dumper.py
datapackage_pipelines_aws.egg-info/PKG-INFO
datapackage_pipelines_aws.egg-info/SOURCES.txt
datapackage_pipelines_aws.egg-info/dependency_links.txt
datapackage_pipelines_aws.egg-info/not-zip-safe
datapackage_pipelines_aws.egg-info/requires.txt
datapackage_pipelines_aws.egg-info/top_level.txt
datapackage_pipelines_aws/processors/__init__.py
datapackage_pipelines_aws/processors/change_acl.py
datapackage_pipelines_aws/processors/dump/__init__.py
datapackage_pipelines_aws/processors/dump/to_s3.py