Metadata-Version: 1.1
Name: datapackage-pipelines-aws
Version: 0.0.20
Summary: {{ DESCRIPTION }}
Home-page: https://github.com/frictionlessdata/datapackage_pipelines_aws
Author: Open Knowledge International
Author-email: UNKNOWN
License: MIT
Keywords: data,analytics
Platform: UNKNOWN
Classifier: Development Status :: 4 - Beta
Classifier: Environment :: Web Environment
Classifier: Intended Audience :: Developers
Classifier: License :: OSI Approved :: MIT License
Classifier: Operating System :: OS Independent
Classifier: Programming Language :: Python :: 3.6
Classifier: Topic :: Internet :: WWW/HTTP :: Dynamic Content
Classifier: Topic :: Software Development :: Libraries :: Python Modules
